{
  "UserAgent": "MobileHub/1.0",
  "Version": "1.0",
  "CredentialsProvider": {
    "CognitoIdentity": {
      "Default": {
        "PoolId": "ap-southeast-1:da5666a3-e948-4f0c-b31c-a89b831e489c",
        "Region": "ap-southeast-1"
      }
    }
  },
  "IdentityManager": {
    "Default": {}
  },
  "PinpointAnalytics": {
    "Default": {
      "AppId": "b080c5f132c24c52930fe52cf32b7038",
      "Region": "us-east-1"
    }
  },
  "PinpointTargeting": {
    "Default": {
      "Region": "us-east-1"
    }
  },
  "GoogleSignIn": {
    "ClientId-WebApp": "823609092380-rpl47c67pfu4pc82sop687qg1lmpqabv.apps.googleusercontent.com",
    "ClientId-iOS": "823609092380-p78k8mcghdtgo8452uhhi6mka0frpc0i.apps.googleusercontent.com",
    "Permissions": "email,profile,openid"
  }
}